EZLog/__init__.py
EZLog/ezlog.py
EZLog_RCL-1.0.0.0.dist-info/LICENSE
EZLog_RCL-1.0.0.0.dist-info/METADATA
EZLog_RCL-1.0.0.0.dist-info/WHEEL
EZLog_RCL-1.0.0.0.dist-info/top_level.txt
EZLog_RCL-1.0.0.0.dist-info/RECORD
