Metadata-Version: 2.1
Name: EZLog-RCL
Version: 1.0.0.0
Summary: an easy logger without setting on PIP platform
Home-page: https://github.com/Rickiarty/EZLog_Python
Author: Rei-Chi Lin
Author-email: fatalframe0719@gmail.com
License: UNKNOWN
Platform: UNKNOWN
Classifier: Programming Language :: Python :: 3
Classifier: License :: OSI Approved :: MIT License
Classifier: Operating System :: OS Independent
License-File: LICENSE
